Workbook

Sheet Dashboard
A1: MMM— August 2026 Content Calendar
A4: Client | B4: Social Posts (Target) | C4: Social Posts Planned This Month | D4: Social Posts Published | E4: Social Progress | F4: Blogs (Target) | G4: Blogs Published | H4: Blog Progress | I4: Notes
A5: My Health | B5: 20 | C5: =COUNTIF('All Content'!$A:$A,A5) -> 20 | D5: =COUNTIF('My Health'!M:M, "Published") -> 0 | E5: =IF(B5=0,"N/A",D5/B5) -> 0 | F5: 8 | H5: =IF(F5=0,"N/A",G5/F5) -> 0 | I5: =IF(B5=0,"Blog-only client — no social calendar this month",IF(B5>C5,"Needs "&(B5-C5)&" more post(s) scheduled to hit target","Calendar complete for target")) -> Calendar complete for target
A6: Journey Wellness | B6: 0 | C6: =COUNTIF('All Content'!$A:$A,A6) -> 0 | E6: =IF(B6=0,"N/A",D6/B6) -> N/A | F6: 8 | H6: =IF(F6=0,"N/A",G6/F6) -> 0 | I6: =IF(B6=0,"Blog-only client — no social calendar this month",IF(B6>C6,"Needs "&(B6-C6)&" more post(s) scheduled to hit target","Calendar complete for target")) -> Blog-only client — no social calendar this month
A7: Sikkini | B7: 30 | C7: =COUNTIF('All Content'!$A:$A,A7) -> 30 | D7: =COUNTIF(Sikkini!M:M, "Published") -> 0 | E7: =IF(B7=0,"N/A",D7/B7) -> 0 | F7: 8 | H7: =IF(F7=0,"N/A",G7/F7) -> 0 | I7: =IF(B7=0,"Blog-only client — no social calendar this month",IF(B7>C7,"Needs "&(B7-C7)&" more post(s) scheduled to hit target","Calendar complete for target")) -> Calendar complete for target
A8: Fika Time | B8: 15 | C8: =COUNTIF('All Content'!$A:$A,A8) -> 7 | D8: =COUNTIF('Fika Time'!H:H, "Published") -> 0 | E8: =IF(B8=0,"N/A",D8/B8) -> 0 | F8: 0 | H8: =IF(F8=0,"N/A",G8/F8) -> N/A | I8: =IF(B8=0,"Blog-only client — no social calendar this month",IF(B8>C8,"Needs "&(B8-C8)&" more post(s) scheduled to hit target","Calendar complete for target")) -> Needs 8 more post(s) scheduled to hit target
A9: Man Made Marketing | B9: 15 | C9: =COUNTIF('All Content'!$A:$A,A9) -> 15 | D9: =COUNTIF('Man Made Marketing'!M:M, "Published") -> 0 | E9: =IF(B9=0,"N/A",D9/B9) -> 0 | F9: 7 | H9: =IF(F9=0,"N/A",G9/F9) -> 0 | I9: =IF(B9=0,"Blog-only client — no social calendar this month",IF(B9>C9,"Needs "&(B9-C9)&" more post(s) scheduled to hit target","Calendar complete for target")) -> Calendar complete for target
A10: Eshopify Fulfillment | B10: 0 | C10: =COUNTIF('All Content'!$A:$A,A10) -> 0 | E10: =IF(B10=0,"N/A",D10/B10) -> N/A | F10: 8 | H10: =IF(F10=0,"N/A",G10/F10) -> 0 | I10: =IF(B10=0,"Blog-only client — no social calendar this month",IF(B10>C10,"Needs "&(B10-C10)&" more post(s) scheduled to hit target","Calendar complete for target")) -> Blog-only client — no social calendar this month
A12: Legend
A13: Green cells = enter manual data here (e.g., Blogs)
A14: "Planned" = posts scheduled in this workbook's calendar tabs
A15: "Published" = automatically counted from client tabs
A16: Journey Wellness & Eshopify Fulfillment are blog-only accounts

Sheet My Health
A1: Post # | B1: Week | C1: Platform | D1: Format | E1: Audience | F1: Funnel | G1: Pillar | H1: Topic | I1: Hook | J1: Slide/Reel Breakdown | K1: Visual Direction | L1: CTA | M1: Status
A2: 1 | B2: 1 | C2: Instagram | D2: Carousel | E2: Premium Adults | F2: Awareness | G2: Longevity | H2: The Science of Healthy Aging | I2: Aging is optional. Decline isn't. | J2: Problem > Habits > CTA | K2: Editorial wellness | L2: Learn More | M2: Planned
A3: 2 | B3: 1 | C3: Instagram | D3: Static | E3: Professionals | F3: Awareness | G3: Preventive Care | H3: Prevention Is Your Greatest Investment | I3: Don't wait for symptoms. | J3: Hero statement | K3: Luxury clinic aesthetic | L3: Book Consultation | M3: Planned
A4: 3 | B4: 1 | C4: Instagram | D4: Reel | E4: Professionals | F4: Engagement | G4: Lifestyle | H4: Morning Habits for Longevity | I4: Your first hour matters. | J4: Routine > Tips | K4: Cinematic morning visuals | L4: Follow | M4: Planned
A5: 4 | B5: 1 | C5: Instagram | D5: Carousel | E5: Families | F5: Education | G5: Nutrition | H5: Foods That Support Healthy Aging | I5: Eat for the next 20 years. | J5: Food > Benefits > CTA | K5: Minimal editorial | L5: Save | M5: Planned
A6: 5 | B6: 1 | C6: Instagram | D6: Static | E6: Premium Audience | F6: Trust | G6: Brand | H6: Why Choose My Health | I6: Healthcare, reimagined. | J6: Hero + key benefits | K6: Premium white & green | L6: Learn More | M6: Planned
A7: 6 | B7: 2 | C7: Instagram | D7: Reel | E7: Professionals | F7: Engagement | G7: Movement | H7: Move More, Live Better | I7: Every step counts. | J7: Exercise > Benefits | K7: Lifestyle cinematography | L7: Share | M7: Planned
A8: 7 | B8: 2 | C8: Instagram | D8: Carousel | E8: Adults 35+ | F8: Education | G8: Health Screening | H8: What Does a Preventive Check-up Include? | I8: Know your numbers before they matter. | J8: Screening > Explanation | K8: Medical infographic | L8: Book Assessment | M8: Planned
A9: 8 | B9: 2 | C9: Instagram | D9: Static | E9: Executives | F9: Awareness | G9: Sleep | H9: Sleep Is Your Best Recovery Tool | I9: Better sleep. Better life. | J9: Single insight | K9: Editorial bedroom scene | L9: Save | M9: Planned
A10: 9 | B10: 2 | C10: Instagram | D10: Reel | E10: Professionals | F10: Trust | G10: Facility | H10: Inside My Health | I10: A premium healthcare experience. | J10: Walkthrough | K10: Bright luxury interiors | L10: Book Visit | M10: Planned
A11: 10 | B11: 3 | C11: Instagram | D11: Carousel | E11: Adults | F11: Education | G11: Heart Health | H11: 5 Silent Risk Factors | I11: You can't feel everything. | J11: Risks > Prevention | K11: Clean infographic | L11: Save | M11: Planned
A12: 11 | B12: 3 | C12: Instagram | D12: Static | E12: Professionals | F12: Awareness | G12: Hydration | H12: Your Body Needs More Than Water | I12: Hydration impacts every cell. | J12: Hero statement | K12: Macro wellness photography | L12: Follow | M12: Planned
A13: 12 | B13: 3 | C13: Instagram | D13: Reel | E13: Premium Audience | F13: Engagement | G13: Technology | H13: Advanced Health Screening | I13: Prevention powered by technology. | J13: Device > Experience | K13: Luxury medical tech | L13: Learn More | M13: Planned
... A21: 20 | B21: 5 | C21: Instagram | D21: Static | E21: Premium Audience | F21: Conversion | G21: Brand | H21: Invest in Your Future Self | I21: Your future health starts today. | J21: Hero visual + CTA | K21: Luxury wellness campaign | L21: Book Consultation | M21: Planned

Sheet Sikkini
A1: Post # | B1: Week | C1: Platform | D1: Format | E1: Audience | F1: Funnel | G1: Pillar | H1: Topic | I1: Hook | J1: Slide/Reel Breakdown | K1: Visual Direction | L1: CTA | M1: Status
A2: 1 | B2: 1 | C2: Instagram | D2: Carousel | E2: B2B | F2: Awareness | G2: Business Value | H2: Why Commercial Kitchens Should Stop Buying Knives | I2: Stop Buying. Start Exchanging. | J2: Problem>Cost>Solution>CTA | K2: Editorial infographic | L2: Book Trial | M2: Planned
A3: 2 | B3: 1 | C3: Instagram | D3: Reel | E3: B2C | F3: Awareness | G3: Knife Skills | H3: Tomato Slice Test | I3: One Slice Says It All. | J3: Hook>Slowmo>CTA | K3: Macro cinematography | L3: Follow | M3: Planned
A4: 3 | B4: 1 | C4: Instagram | D4: Static | E4: B2B | F4: Consideration | G4: Service | H4: What is SIKKINI? | I4: Knife Exchange Simplified. | J4: Flow diagram | K4: Industrial graphics | L4: Learn More | M4: Planned
A5: 4 | B5: 1 | C5: Instagram | D5: Carousel | E5: B2B | F5: Awareness | G5: Costs | H5: Hidden Cost of Dull Knives | I5: You're Losing More Than Sharpness. | J5: Pain>Stats>Solution | K5: Bold data visuals | L5: Book Trial | M5: Planned
A6: 5 | B6: 1 | C6: Instagram | D6: Reel | E6: B2B | F6: Consideration | G6: Operations | H6: Exchange Day | I6: 30 Seconds. Zero Downtime. | J6: Arrival>Swap>Exit | K6: Documentary | L6: Book Demo | M6: Planned
A7: 6 | B7: 1 | C7: Instagram | D7: Carousel | E7: B2B | F7: Education | G7: Operations | H7: How the Exchange Works | I7: Supply → Exchange → Sharpen → Repeat | J7: 7-slide process | K7: Minimal icons | L7: Learn More | M7: Planned
A8: 7 | B8: 1 | C8: Instagram | D8: Static | E8: B2C | F8: Education | G8: Safety | H8: Knife Safety Tip | I8: Sharp Knives Are Safer. | J8: Single tip | K8: White background | L8: Save | M8: Planned
A9: 8 | B9: 2 | C9: Instagram | D9: Reel | E9: B2C | F9: Engagement | G9: Precision | H9: Paper Cutting Test | I9: Is Your Knife Really Sharp? | J9: ASMR | K9: Close-up | L9: Follow | M9: Planned
A10: 9 | B10: 2 | C10: Instagram | D10: Carousel | E10: B2B | F10: Education | G10: Hygiene | H10: Color-Coded Knives | I10: Prevent Cross Contamination. | J10: Problem>Colors | K10: Color system | L10: Contact | M10: Planned
A11: 10 | B11: 2 | C11: Instagram | D11: Reel | E11: B2B | F11: Trust | G11: Workshop | H11: Inside Tormek T8 | I11: Precision You Can't See. | J11: Workshop tour | K11: Steel textures | L11: Learn | M11: Planned
A12: 11 | B12: 2 | C12: Instagram | D12: Static | E12: B2B | F12: Trust | G12: Brand | H12: Meet the Team | I12: Experts Behind Every Blade. | J12: Portrait | K12: Industrial | L12: Meet Us | M12: Planned
A13: 12 | B13: 2 | C13: Instagram | D13: Carousel | E13: B2B | F13: Consideration | G13: Products | H13: Knife Arsenal | I13: One Service. Every Knife. | J13: Knife cards | K13: Black/steel | L13: Contact | M13: Planned
... A31: 30 | B31: 5 | C31: Instagram | D31: Reel | E31: B2B | F31: Conversion | G31: Campaign | H31: Book Your Trial | I31: Ready to Upgrade? | J31: Montage | K31: Brand film | L31: Book Trial | M31: Planned

Sheet Fika Time
A1: Week | B1: Date | C1: Campaign | D1: Content Idea | E1: Format | F1: Objective | G1: Reference | H1: Status | I1: Reference.1 | J1: Music
A2: Week 1 | B2: 3 Aug | C2: Freshly Baked Every Day | D2: Fresh from the Oven | E2: Carousel | F2: Show freshness & craftsmanship | G2: https://www.instagram.com/reel/DadCWI0omOC/?utm_source=ig_web_copy_link&igsh=MzRlODBiNWFlZA== | H2: 🟡 Planned | I2: https://www.instagram.com/reel/DZ7fH_Sojs6/?utm_source=ig_web_copy_link&igsh=MzRlODBiNWFlZA== | J2: https://www.instagram.com/reels/audio/1044245831898294/
A3: Week 1 | B3: 5 Aug | C3: Atmosphere & Fresh Food | D3: Brand Awareness Film | E3: Reel | F3: Introduce Fika Time lifestyle | G3: https://www.instagram.com/reel/DYwbr2JEXNV/ | H3: 🟡 Planned | J3: https://www.instagram.com/reels/audio/1231203088367810/
A4: Week 1 | B4: 7 Aug | C4: Freshly Baked Every Day | D4: Coffee & Cake Pairing | E4: Static | F4: Highlight signature pairing | G4: https://www.instagram.com/reel/DQV5MI0k66T/?utm_source=ig_web_copy_link&igsh=MzRlODBiNWFlZA== | H4: 🟡 Planned | I4: https://www.instagram.com/reel/DPGVte0FPvp/?utm_source=ig_web_copy_link&igsh=MzRlODBiNWFlZA== | J4: https://www.instagram.com/reels/audio/2408760532948877/
A5: Week 2 | B5: 10 Aug | C5: Atmosphere & Fresh Food | D5: Brunch Moments | E5: Reel | F5: Lifestyle & ambience | G5: https://www.instagram.com/reel/DPvR1dgjILi/ | H5: 🟡 Planned | I5: https://www.instagram.com/reel/DPTDshcCVNJ/?utm_source=ig_web_copy_link&igsh=MzRlODBiNWFlZA== | J5: https://www.instagram.com/reels/audio/1541930454055091/
A6: Week 2 | B6: 12 Aug | C6: Back to School | D6: Fuel Your Morning | E6: Reel | F6: Seasonal awareness | H6: 🟡 Planned | J6: https://www.instagram.com/reels/audio/698753584644420/
A7: Week 2 | B7: 14 Aug | C7: Freshly Baked Every Day | D7: Dessert Spotlight | E7: Static | F7: Feature signature dessert | G7: https://www.instagram.com/reel/DHP9go0hpay/?utm_source=ig_web_copy_link&igsh=MzRlODBiNWFlZA== | H7: 🟡 Planned | J7: https://www.instagram.com/reels/audio/4216755795268858/
A8: Week 2 | B8: 16 Aug | C8: Atmosphere & Fresh Food | D8: Slow Down at Fika | E8: Reel | F8: Brand experience | H8: 🟡 Planned | J8: https://www.instagram.com/reels/audio/1344931484516320/

Sheet Man Made Marketing
A1: Post # | B1: Week | C1: Platform | D1: Format | E1: Audience | F1: Funnel | G1: Pillar | H1: Topic | I1: Hook | J1: Slide/Reel Breakdown | K1: Visual Direction | L1: CTA | M1: Status
A2: 1 | B2: 1 | C2: Instagram | D2: Static | E2: Business Owners | F2: Awareness | G2: Color Psychology | H2: Blue Builds Trust | I2: Why do banks love blue? | J2: Hero statement + examples | K2: Editorial, blue gradient, minimal | L2: Follow | M2: Planned
A3: 2 | B3: 1 | C3: Instagram | D3: Reel | E3: Business Owners | F3: Awareness | G3: Brand Breakdown | H3: Why Apple Never Discounts | I3: Premium isn't about price | J3: Hook > Analysis > Takeaway | K3: Clean motion graphics | L3: Save | M3: Planned
A4: 3 | B4: 1 | C4: Instagram | D4: Carousel | E4: Startups | F4: Education | G4: Branding | H4: 5 Branding Mistakes | I4: Is your brand making these mistakes? | J4: Mistake > Example > Fix | K4: Minimal editorial | L4: Share | M4: Planned
A5: 4 | B5: 1 | C5: Instagram | D5: Reel | E5: Business Owners | F5: Engagement | G5: Color Psychology | H5: Red Makes You Hungry | I5: There's a reason restaurants use red | J5: Hook > Examples > Psychology | K5: Fast-paced motion | L5: Follow | M5: Planned
A6: 5 | B6: 2 | C6: Instagram | D6: Static | E6: SMEs | F6: Awareness | G6: Marketing | H6: People Buy Stories | I6: Stop selling. Start storytelling. | J6: Hero quote | K6: Black & white editorial | L6: Learn More | M6: Planned
A7: 6 | B7: 2 | C7: Instagram | D7: Carousel | E7: Business Owners | F7: Education | G7: Marketing Strategy | H7: Why Consistency Wins | I7: The strongest brands repeat | J7: Principle > Examples > Action | K7: Grid layout | L7: Save | M7: Planned
A8: 7 | B8: 2 | C8: Instagram | D8: Reel | E8: Entrepreneurs | F8: Engagement | G8: Logo Design | H8: Can You Recognize This Logo? | I8: Remove the name, keep the shape | J8: Quiz > Reveal | K8: Motion graphics | L8: Comment | M8: Planned
A9: 8 | B9: 2 | C9: Instagram | D9: Static | E9: Startups | F9: Consideration | G9: Design | H9: First Impressions Matter | I9: Your website has 5 seconds | J9: Hero statement | K9: Minimal UI-inspired layout | L9: Contact | M9: Planned
A10: 9 | B10: 3 | C10: Instagram | D10: Carousel | E10: Marketing Teams | F10: Education | G10: Typography | H10: Fonts That Build Trust | I10: Typography changes perception | J10: Comparison slides | K10: Editorial typography | L10: Save | M10: Planned
A11: 10 | B11: 3 | C11: Instagram | D11: Reel | E11: Business Owners | F11: Awareness | G11: Brand Breakdown | H11: Why Nike Doesn't Sell Shoes | I11: They're selling identity | J11: Hook > Campaigns > Lesson | K11: Dynamic motion | L11: Follow | M11: Planned
A12: 11 | B12: 3 | C12: Instagram | D12: Static | E12: Businesses | F12: Trust | G12: Agency | H12: What We Actually Do | I12: More than social media | J12: Service overview | K12: Minimal iconography | L12: Learn More | M12: Planned
A13: 12 | B13: 3 | C13: Instagram | D13: Carousel | E13: Business Owners | F13: Consideration | G13: Website Design | H13: Signs Your Website Needs a Redesign | I13: Losing customers without knowing? | J13: Problems > Fixes | K13: Clean UI mockups | L13: Contact | M13: Planned
... A16: 15 | B16: 4 | C16: Instagram | D16: Reel | E16: Business Owners | F16: Conversion | G16: Agency Brand | H16: Let's Build Something Memorable | I16: Your next customer is watching | J16: Showreel > Portfolio > CTA | K16: High-end agency reel | L16: Book a Discovery Call | M16: Planned

Sheet All Content
A1: Client | B1: Week | C1: Date | D1: Platform | E1: Format | F1: Audience | G1: Funnel Stage | H1: Campaign / Pillar | I1: Topic / Content Idea | J1: Hook | K1: CTA | L1: Status | M1: Reference Link | N1: Notes
A2: Fika Time | B2: 1 | C2: 46237 | D2: Instagram | E2: Carousel | H2: Freshly Baked Every Day | I2: Fresh from the Oven | L2: 🟡 Planned | M2: https://www.instagram.com/reel/DadCWI0omOC/?utm_source=ig_web_copy_link&igsh=MzRlODBiNWFlZA== | N2: Show freshness & craftsmanship
A3: Fika Time | B3: 1 | C3: 46239 | D3: Instagram | E3: Reel | H3: Atmosphere & Fresh Food | I3: Brand Awareness Film | L3: 🟡 Planned | M3: https://www.instagram.com/reel/DYwbr2JEXNV/ | N3: Introduce Fika Time lifestyle
A4: Fika Time | B4: 1 | C4: 46241 | D4: Instagram | E4: Static | H4: Freshly Baked Every Day | I4: Coffee & Cake Pairing | L4: 🟡 Planned | M4: https://www.instagram.com/reel/DQV5MI0k66T/?utm_source=ig_web_copy_link&igsh=MzRlODBiNWFlZA== | N4: Highlight signature pairing
A5: Fika Time | B5: 2 | C5: 46244 | D5: Instagram | E5: Reel | H5: Atmosphere & Fresh Food | I5: Brunch Moments | L5: 🟡 Planned | M5: https://www.instagram.com/reel/DPvR1dgjILi/ | N5: Lifestyle & ambience
A6: Fika Time | B6: 2 | C6: 46246 | D6: Instagram | E6: Reel | H6: Back to School | I6: Fuel Your Morning | L6: 🟡 Planned | N6: Seasonal awareness
A7: Fika Time | B7: 2 | C7: 46248 | D7: Instagram | E7: Static | H7: Freshly Baked Every Day | I7: Dessert Spotlight | L7: 🟡 Planned | M7: https://www.instagram.com/reel/DHP9go0hpay/?utm_source=ig_web_copy_link&igsh=MzRlODBiNWFlZA== | N7: Feature signature dessert
A8: Fika Time | B8: 2 | C8: 46250 | D8: Instagram | E8: Reel | H8: Atmosphere & Fresh Food | I8: Slow Down at Fika | L8: 🟡 Planned | N8: Brand experience
A9: Man Made Marketing | B9: 1 | D9: Instagram | E9: Static | F9: Business Owners | G9: Awareness | H9: Color Psychology | I9: Blue Builds Trust | J9: Why do banks love blue? | K9: Follow | L9: Planned
A10: Man Made Marketing | B10: 1 | D10: Instagram | E10: Reel | F10: Business Owners | G10: Awareness | H10: Brand Breakdown | I10: Why Apple Never Discounts | J10: Premium isn't about price | K10: Save | L10: Planned
A11: Man Made Marketing | B11: 1 | D11: Instagram | E11: Carousel | F11: Startups | G11: Education | H11: Branding | I11: 5 Branding Mistakes | J11: Is your brand making these mistakes? | K11: Share | L11: Planned
A12: Man Made Marketing | B12: 1 | D12: Instagram | E12: Reel | F12: Business Owners | G12: Engagement | H12: Color Psychology | I12: Red Makes You Hungry | J12: There's a reason restaurants use red | K12: Follow | L12: Planned
A13: Man Made Marketing | B13: 2 | D13: Instagram | E13: Static | F13: SMEs | G13: Awareness | H13: Marketing | I13: People Buy Stories | J13: Stop selling. Start storytelling. | K13: Learn More | L13: Planned
A14: Man Made Marketing | B14: 2 | D14: Instagram | E14: Carousel | F14: Business Owners | G14: Education | H14: Marketing Strategy | I14: Why Consistency Wins | J14: The strongest brands repeat | K14: Save | L14: Planned
A15: Man Made Marketing | B15: 2 | D15: Instagram | E15: Reel | F15: Entrepreneurs | G15: Engagement | H15: Logo Design | I15: Can You Recognize This Logo? | J15: Remove the name, keep the shape | K15: Comment | L15: Planned
A16: Man Made Marketing | B16: 2 | D16: Instagram | E16: Static | F16: Startups | G16: Consideration | H16: Design | I16: First Impressions Matter | J16: Your website has 5 seconds | K16: Contact | L16: Planned
A17: Man Made Marketing | B17: 3 | D17: Instagram | E17: Carousel | F17: Marketing Teams | G17: Education | H17: Typography | I17: Fonts That Build Trust | J17: Typography changes perception | K17: Save | L17: Planned
A18: Man Made Marketing | B18: 3 | D18: Instagram | E18: Reel | F18: Business Owners | G18: Awareness | H18: Brand Breakdown | I18: Why Nike Doesn't Sell Shoes | J18: They're selling identity | K18: Follow | L18: Planned
A19: Man Made Marketing | B19: 3 | D19: Instagram | E19: Static | F19: Businesses | G19: Trust | H19: Agency | I19: What We Actually Do | J19: More than social media | K19: Learn More | L19: Planned
A20: Man Made Marketing | B20: 3 | D20: Instagram | E20: Carousel | F20: Business Owners | G20: Consideration | H20: Website Design | I20: Signs Your Website Needs a Redesign | J20: Losing customers without knowing? | K20: Contact | L20: Planned
... A73: Sikkini | B73: 5 | D73: Instagram | E73: Reel | F73: B2B | G73: Conversion | H73: Campaign | I73: Book Your Trial | J73: Ready to Upgrade? | K73: Book Trial | L73: Planned
